photocollage/__init__.py
photocollage/artwork.py
photocollage/collage.py
photocollage/gtkgui.py
photocollage/render.py
photocollage/locale/bg/LC_MESSAGES/photocollage.mo
photocollage/locale/cs/LC_MESSAGES/photocollage.mo
photocollage/locale/de/LC_MESSAGES/photocollage.mo
photocollage/locale/es/LC_MESSAGES/photocollage.mo
photocollage/locale/fr/LC_MESSAGES/photocollage.mo
photocollage/locale/it/LC_MESSAGES/photocollage.mo
photocollage/locale/nl/LC_MESSAGES/photocollage.mo
photocollage/locale/pl/LC_MESSAGES/photocollage.mo
photocollage/locale/pt_BR/LC_MESSAGES/photocollage.mo
photocollage/locale/ru/LC_MESSAGES/photocollage.mo
photocollage/locale/uk/LC_MESSAGES/photocollage.mo
photocollage-1.5.0.data/data/share/appdata/photocollage.appdata.xml
photocollage-1.5.0.data/data/share/applications/photocollage.desktop
photocollage-1.5.0.data/data/share/icons/hicolor/128x128/apps/photocollage.png
photocollage-1.5.0.data/data/share/icons/hicolor/16x16/apps/photocollage.png
photocollage-1.5.0.data/data/share/icons/hicolor/22x22/apps/photocollage.png
photocollage-1.5.0.data/data/share/icons/hicolor/24x24/apps/photocollage.png
photocollage-1.5.0.data/data/share/icons/hicolor/256x256/apps/photocollage.png
photocollage-1.5.0.data/data/share/icons/hicolor/32x32/apps/photocollage.png
photocollage-1.5.0.data/data/share/icons/hicolor/48x48/apps/photocollage.png
photocollage-1.5.0.data/data/share/icons/hicolor/64x64/apps/photocollage.png
photocollage-1.5.0.data/data/share/icons/hicolor/scalable/apps/photocollage.svg
photocollage-1.5.0.dist-info/licenses/LICENSE
photocollage-1.5.0.dist-info/METADATA
photocollage-1.5.0.dist-info/WHEEL
photocollage-1.5.0.dist-info/entry_points.txt
photocollage-1.5.0.dist-info/top_level.txt
photocollage-1.5.0.dist-info/RECORD
