Metadata-Version: 2.4
Name: photocollage
Version: 1.5.0
Summary: Graphical tool to make photo collage posters
Author: Adrien Vergé
License: GPL-2.0-or-later
Project-URL: homepage, https://github.com/adrienverge/PhotoCollage
Project-URL: repository, https://github.com/adrienverge/PhotoCollage
Keywords: photocollage,photo,collage,poster,mosaic,image
Classifier: Development Status :: 5 - Production/Stable
Classifier: Environment :: X11 Applications :: GTK
Classifier: Intended Audience :: End Users/Desktop
Classifier: Programming Language :: Python
Classifier: Topic :: Multimedia :: Graphics
Requires-Python: >=3.9
License-File: LICENSE
Requires-Dist: Pillow
Requires-Dist: pycairo
Provides-Extra: dev
Requires-Dist: flake8; extra == "dev"
Requires-Dist: flake8-import-order; extra == "dev"
Dynamic: license-file
